qq_sched_send_message/Erorr.py
qq_sched_send_message/Sched.py
qq_sched_send_message/SendMsg.py
qq_sched_send_message/__init__.py
py_qq_sched_send_msg-0.0.8.1.dist-info/METADATA
py_qq_sched_send_msg-0.0.8.1.dist-info/WHEEL
py_qq_sched_send_msg-0.0.8.1.dist-info/top_level.txt
py_qq_sched_send_msg-0.0.8.1.dist-info/RECORD
