Metadata-Version: 2.1
Name: py-qq-sched-send-msg
Version: 0.0.8.1
Summary: 这是一个可以快捷地向多个QQ好友或群组发消息的包
Home-page: https://github.com/Sugobet/QQ-Sched-send-message
Author: Sugobet
Author-email: 321355478@qq.com
License: UNKNOWN
Platform: UNKNOWN
Classifier: Programming Language :: Python :: 3
Classifier: License :: OSI Approved :: MIT License
Classifier: Operating System :: OS Independent
Requires-Python: >=3.6
